{
  "10.9999/nonexistentdoi": {},
  "10.1080/14680777.2017.1399430": {
    "title": "Compassion in Kim Longinotto’s documentary practice",
    "authors": [
      "George S. Larke-Walsh"
    ],
    "publisher": "Informa UK Limited",
    "journal": "Feminist Media Studies",
    "published_date": "2019-1-2",
    "subjects": []
  },
  "10.4000/hamsa.693": {
    "title": "Jews of Berber Origin: Myth or Reality?",
    "authors": [
      "Alexander Beider"
    ],
    "publisher": "OpenEdition",
    "journal": "Hamsa",
    "published_date": "2017",
    "subjects": []
  },
  "10.3917/tdm.036.0156": {},
  "10.3917/sh.311.0021": {},
  "10.3917/cdge.052.0119": {},
  "10.3917/eres.welze.2011.01.0041": {},
  "10.3917/rfsp.573.0459": {
    "title": "L'électorat de Nicolas Sarkozy : « rupture tranquille » ou syncrétisme tourmenté ?",
    "authors": [
      "Sylvie Strudel"
    ],
    "publisher": "CAIRN",
    "journal": "Revue française de science politique",
    "published_date": "2007-8-28",
    "subjects": []
  },
  "10.3917/her.107.0147": {
    "title": "La politique de la montagne en France",
    "authors": [
      "Céline Broggio"
    ],
    "publisher": "CAIRN",
    "journal": "Hérodote",
    "published_date": "2002-10-17",
    "subjects": []
  },
  "10.3406/rfsp.1977.393751": {
    "title": "Une ou deux droites à Paris ? Les élections municipales de 1977 et la restructuration du bloc conservateur",
    "authors": [
      "Élisabeth Dupoirier"
    ],
    "publisher": "PERSEE Program",
    "journal": "Revue française de science politique",
    "published_date": "1977",
    "subjects": []
  },
  "10.3917/pouv.110.0061": {
    "title": "Élections et électeurs à Paris. Évolutions sociologiques et ruptures électorales 1977-2002",
    "authors": [
      "Éric Perraudeau"
    ],
    "publisher": "CAIRN.INFO",
    "journal": "Pouvoirs",
    "published_date": "2004-8-27",
    "subjects": []
  },
  "10.3917/herm.082.0169": {
    "title": "Les musiques de campagne : des hymnes aux ritournelles publicitaires",
    "authors": [
      "Thibault Jeandemange"
    ],
    "publisher": "CAIRN",
    "journal": "Hermès",
    "published_date": "2018",
    "subjects": []
  },
  "10.3406/rfsp.1990.394523": {
    "title": "Le « moment néo-libéral » du RPR : essai d'interprétation",
    "authors": [
      "Jean Baudouin"
    ],
    "publisher": "PERSEE Program",
    "journal": "Revue française de science politique",
    "published_date": "1990",
    "subjects": []
  },
  "10.3917/anso.012.0355": {
    "title": "La communication politique en France : un champ de recherche qui doit encore s'imposer",
    "authors": [
      "Arnaud Mercier"
    ],
    "publisher": "CAIRN",
    "journal": "L'Année sociologique",
    "published_date": "2001-9-1",
    "subjects": []
  },
  "10.3917/parl.007.0121": {
    "title": "La stratégie de communication de François Mitterrand en 1988",
    "authors": [
      "Olivier Rouquan"
    ],
    "publisher": "CAIRN",
    "journal": "Parlement[s], Revue d'histoire politique",
    "published_date": "2007-3-1",
    "subjects": []
  },
  "10.3917/cite.081.0169": {
    "title": "L’apothéose de Jacques Chirac, un révélateur des impasses de la politique française contemporaine",
    "authors": [
      "Mathias Bernard"
    ],
    "publisher": "CAIRN",
    "journal": "Cités",
    "published_date": "2020-3-6",
    "subjects": []
  }
}